CHANGELOG.md
MANIFEST.in
README.md
findup.py
setup.py
findup.egg-info/PKG-INFO
findup.egg-info/SOURCES.txt
findup.egg-info/dependency_links.txt
findup.egg-info/top_level.txt