Metadata-Version: 1.1
Name: findup
Version: 0.3.0
Summary: Find the first file matching a given pattern in the current directory or the nearest ancestor directory.
Home-page: https://github.com/todddeluca/python-findup
Author: Todd Francis DeLuca
Author-email: todddeluca@yahoo.com
License: MIT
Keywords: python findup glob cwd directory pattern
Platform: UNKNOWN
Classifier: License :: OSI Approved :: MIT License
Classifier: Development Status :: 3 - Alpha
Classifier: Programming Language :: Python :: 2
Classifier: Programming Language :: Python :: 2.7
Classifier: Programming Language :: Python :: 3
Classifier: Programming Language :: Python :: 3.3
